{
    "Releases": [
        {
            "Version": "2.0.2",
            "ReleaseDate": "2026-03-26",
            "ChangeLogs": {
                "Added": [
                    "add Windows-only check for scheme feature (#160)"
                ],
                "Fixed": [
                    "handle non-system item and image paths in V1 data import (#162)"
                ],
                "Changed": [
                    "bump version to 2.0.2 (#163)"
                ]
            },
            "ReleaseUrl": "https://github.com/puk06/VRC-Avatar-Explorer/releases/tag/v2.0.2-stable"
        },
        {
            "Version": "2.0.1",
            "ReleaseDate": "2026-03-25",
            "ChangeLogs": {
                "Added": [],
                "Fixed": [],
                "Changed": [
                    "add .NET Runtime license information to THIRD_PARTY_LICENSES.txt (#156)",
                    "bump version to 2.0.1 (#158)"
                ]
            },
            "ReleaseUrl": "https://github.com/puk06/VRC-Avatar-Explorer/releases/tag/v2.0.1-stable"
        },
        {
            "Version": "2.0.0",
            "ReleaseDate": "2026-03-25",
            "ChangeLogs": {
                "Added": [
                    "support releaseUrl from update manifest and use it for update dialog links (#153)"
                ],
                "Fixed": [
                    "use TextParser in SearchFilterBuilder to preserve quoted values (#149)",
                    "make text input take precedence when advanced search is also set (#150)",
                    "improve backup reliability and error handling (#151)"
                ],
                "Changed": [
                    "bump version to 2.0.0 (#152)",
                    "add version tag usage guidelines to README (#154)",
                    "switch stable tag suffix from -release to -stable and update readme policy (#155)"
                ]
            },
            "ReleaseUrl": "https://github.com/puk06/VRC-Avatar-Explorer/releases/tag/v2.0.0-stable"
        },
        {
            "Version": "2.0.0-beta.16",
            "ReleaseDate": "2026-03-25",
            "ChangeLogs": {
                "Added": [],
                "Fixed": [
                    "remove outdated font license information and related credits from THIRD_PARTY_LICENSES.txt (#138)",
                    "correct null check for confirmation dialog result in asset removal (#140)",
                    "isolate selected item id per MainWindow overlay to avoid cross-overlay overwrite (#141)",
                    "await data-copy confirmation flow when applying settings (#142)",
                    "rename thumbnail key typo and add item DB migration (#143)",
                    "ensure search index reflects avatar DB changes before refresh (#144)",
                    "refresh search index after replacing supported avatars (#145)",
                    "propagate AddItemPaths failure in EditItem (#146)"
                ],
                "Changed": [
                    "update installation instructions for Windows and non-Windows platforms (#139)",
                    "reduce importer CPU spikes by throttling copy parallelism (#147)",
                    "bump version to 2.0.0-beta.16 (#148)"
                ]
            },
            "ReleaseUrl": "https://github.com/puk06/VRC-Avatar-Explorer/releases/tag/v2.0.0-beta.16"
        },
        {
            "Version": "2.0.0-beta.15",
            "ReleaseDate": "2026-03-24",
            "ChangeLogs": {
                "Added": [],
                "Fixed": [
                    "remove unnecessary privileges override and clean up desktop icon task flags (#135)"
                ],
                "Changed": [
                    "bump version to 2.0.0-beta.15 (#137)"
                ]
            },
            "ReleaseUrl": "https://github.com/puk06/VRC-Avatar-Explorer/releases/tag/v2.0.0-beta.15"
        },
        {
            "Version": "2.0.0-beta.14",
            "ReleaseDate": "2026-03-24",
            "ChangeLogs": {
                "Added": [],
                "Fixed": [],
                "Changed": []
            },
            "ReleaseUrl": "https://github.com/puk06/VRC-Avatar-Explorer/releases/tag/v2.0.0-beta.14"
        }
    ]
}